history4feed/__init__.py
history4feed/asgi.py
history4feed/settings.py
history4feed/urls.py
history4feed/wsgi.py
history4feed/app/__init__.py
history4feed/app/admin.py
history4feed/app/apps.py
history4feed/app/autoschema.py
history4feed/app/models.py
history4feed/app/openapi_params.py
history4feed/app/serializers.py
history4feed/app/settings.py
history4feed/app/tests.py
history4feed/app/utils.py
history4feed/app/views.py
history4feed/app/migrations/0001_initial.py
history4feed/app/migrations/0002_feed_freshness_alter_feed_feed_type.py
history4feed/app/migrations/0003_alter_feed_description.py
history4feed/app/migrations/0004_alter_fulltextjob_status_alter_job_state.py
history4feed/app/migrations/0005_feed_datetime_modified.py
history4feed/app/migrations/0006_job_completion_time.py
history4feed/app/migrations/0007_feed_source_category.py
history4feed/app/migrations/0008_job_extra_data_alter_fulltextjob_status.py
history4feed/app/migrations/0009_feed_use_scrapfly_asp.py
history4feed/app/migrations/__init__.py
history4feed/h4fscripts/__init__.py
history4feed/h4fscripts/build_rss.py
history4feed/h4fscripts/celery.py
history4feed/h4fscripts/exceptions.py
history4feed/h4fscripts/h4f.py
history4feed/h4fscripts/sitemap_helpers.py
history4feed/h4fscripts/task_helper.py
history4feed/h4fscripts/wayback_helpers.py
history4feed/h4fscripts/xml_utils.py
history4feed-1.1.3.dist-info/METADATA
history4feed-1.1.3.dist-info/WHEEL
history4feed-1.1.3.dist-info/licenses/LICENSE
history4feed-1.1.3.dist-info/RECORD
