Metadata-Version: 2.4
Name: history4feed
Version: 1.1.3
Summary: Creates a complete full text historical archive for an RSS or ATOM feed.
Project-URL: Homepage, https://github.com/muchdogesec/history4feed
Project-URL: Issues, https://github.com/muchdogesec/history4feed/issues
Author: dogesec
Maintainer: dogesec
License-File: LICENSE
Classifier: License :: OSI Approved :: Apache Software License
Classifier: Operating System :: OS Independent
Classifier: Programming Language :: Python :: 3
Requires-Python: >=3.9
Requires-Dist: brotlipy>=0.7.0
Requires-Dist: celery>=5.4.0; python_version >= '3.8'
Requires-Dist: dateparser>=1.2.1
Requires-Dist: django-filter>=24.2
Requires-Dist: django>=5.2.3
Requires-Dist: djangorestframework>=3.15.2
Requires-Dist: dogesec-commons
Requires-Dist: drf-spectacular>=0.27.2
Requires-Dist: fake-useragent>=1.5.1
Requires-Dist: gunicorn
Requires-Dist: hyperlink
Requires-Dist: lxml-html-clean>=0.4.1
Requires-Dist: psycopg2-binary>=2.9.10
Requires-Dist: python-dotenv
Requires-Dist: readability-lxml
Requires-Dist: redis
Requires-Dist: requests>=2.32.4
Requires-Dist: whitenoise==6.7.0
Provides-Extra: test
Requires-Dist: pytest; extra == 'test'
Requires-Dist: pytest-cov; extra == 'test'
Requires-Dist: pytest-django; extra == 'test'
Requires-Dist: pytest-subtests; extra == 'test'
Requires-Dist: schemathesis; extra == 'test'
